{
  "challenge_id": "lc_583",
  "source": "leetcode",
  "frontend_id": "583",
  "slug": "delete-operation-for-two-strings",
  "title": "Delete Operation for Two Strings",
  "difficulty": "Medium",
  "acceptance_rate": 65.89185911886403,
  "category": "algorithms",
  "category_title": "Algorithms",
  "topics": [
    {
      "name": "String",
      "slug": "string"
    },
    {
      "name": "Dynamic Programming",
      "slug": "dynamic-programming"
    }
  ],
  "url": "https://leetcode.com/problems/delete-operation-for-two-strings/",
  "supported_languages": [
    "python",
    "cpp",
    "java",
    "csharp",
    "javascript",
    "go",
    "kotlin"
  ],
  "primary_language": "python",
  "runnable_in_coden": true,
  "subsets": [
    "leetcode_all",
    "leetcode_category:algorithms",
    "leetcode_company:google",
    "leetcode_company:infosys",
    "leetcode_topic:dynamic-programming",
    "leetcode_topic:string"
  ],
  "tags": [
    "category:algorithms",
    "company:google",
    "company:infosys",
    "language:cpp",
    "language:csharp",
    "language:go",
    "language:java",
    "language:javascript",
    "language:kotlin",
    "language:python",
    "leetcode",
    "topic:dynamic-programming",
    "topic:string"
  ],
  "company_tags": [
    {
      "name": "Google",
      "slug": "google"
    },
    {
      "name": "Infosys",
      "slug": "infosys"
    }
  ],
  "company_tag_stats": {
    "2": [
      {
        "taggedByAdmin": true,
        "name": "Google",
        "slug": "google",
        "timesEncountered": 2
      },
      {
        "taggedByAdmin": false,
        "name": "Infosys",
        "slug": "infosys",
        "timesEncountered": 2
      }
    ],
    "1": [],
    "3": []
  },
  "neetcode_subsets": []
}
