{
  "challenge_id": "lc_2102",
  "source": "leetcode",
  "frontend_id": "2102",
  "slug": "sequentially-ordinal-rank-tracker",
  "title": "Sequentially Ordinal Rank Tracker",
  "difficulty": "Hard",
  "acceptance_rate": 61.44856356696944,
  "frequency": 0.0,
  "elo_rating": 2158.7683843245,
  "estimated_elo_rating": null,
  "category": "algorithms",
  "category_title": "Algorithms",
  "topics": [
    {
      "name": "Design",
      "slug": "design"
    },
    {
      "name": "Heap (Priority Queue)",
      "slug": "heap-priority-queue"
    },
    {
      "name": "Data Stream",
      "slug": "data-stream"
    },
    {
      "name": "Ordered Set",
      "slug": "ordered-set"
    }
  ],
  "url": "https://leetcode.com/problems/sequentially-ordinal-rank-tracker/",
  "supported_languages": [
    "python",
    "cpp",
    "java",
    "csharp",
    "javascript",
    "go",
    "kotlin"
  ],
  "primary_language": "python",
  "runnable_in_coden": true,
  "subsets": [
    "leetcode_all",
    "leetcode_category:algorithms",
    "leetcode_company:amazon",
    "leetcode_topic:data-stream",
    "leetcode_topic:design",
    "leetcode_topic:heap-priority-queue",
    "leetcode_topic:ordered-set"
  ],
  "tags": [
    "category:algorithms",
    "company:amazon",
    "language:cpp",
    "language:csharp",
    "language:go",
    "language:java",
    "language:javascript",
    "language:kotlin",
    "language:python",
    "leetcode",
    "topic:data-stream",
    "topic:design",
    "topic:heap-priority-queue",
    "topic:ordered-set"
  ],
  "company_tags": [
    {
      "name": "Amazon",
      "slug": "amazon"
    }
  ],
  "company_tag_stats": {
    "3": [
      {
        "taggedByAdmin": true,
        "name": "Amazon",
        "slug": "amazon",
        "timesEncountered": 0
      }
    ],
    "1": [],
    "2": []
  },
  "neetcode_subsets": []
}
