{
  "challenge_id": "lc_275",
  "source": "leetcode",
  "frontend_id": "275",
  "slug": "h-index-ii",
  "title": "H-Index II",
  "difficulty": "Medium",
  "acceptance_rate": 39.74680205723328,
  "frequency": 12.8,
  "elo_rating": null,
  "estimated_elo_rating": 1704.630368,
  "category": "algorithms",
  "category_title": "Algorithms",
  "topics": [
    {
      "name": "Array",
      "slug": "array"
    },
    {
      "name": "Binary Search",
      "slug": "binary-search"
    }
  ],
  "url": "https://leetcode.com/problems/h-index-ii/",
  "supported_languages": [
    "python",
    "cpp",
    "java",
    "csharp",
    "javascript",
    "go",
    "kotlin"
  ],
  "primary_language": "python",
  "runnable_in_coden": true,
  "subsets": [
    "leetcode_all",
    "leetcode_category:algorithms",
    "leetcode_company:facebook",
    "leetcode_studyplan:binary-search",
    "leetcode_studyplan:binary-search:binary-search-117-02xr",
    "leetcode_topic:array",
    "leetcode_topic:binary-search"
  ],
  "tags": [
    "category:algorithms",
    "company:facebook",
    "language:cpp",
    "language:csharp",
    "language:go",
    "language:java",
    "language:javascript",
    "language:kotlin",
    "language:python",
    "leetcode",
    "study_plan:binary-search",
    "study_plan_section:binary-search:binary-search-117-02xr",
    "topic:array",
    "topic:binary-search"
  ],
  "company_tags": [
    {
      "name": "Meta",
      "slug": "facebook"
    }
  ],
  "company_tag_stats": {
    "3": [
      {
        "taggedByAdmin": true,
        "name": "Meta",
        "slug": "facebook",
        "timesEncountered": 0
      }
    ],
    "1": [],
    "2": []
  },
  "study_plans": [
    {
      "plan_slug": "binary-search",
      "plan_name": "Binary Search",
      "section_slug": "binary-search-117-02xr",
      "section_name": "Tricky Invariant",
      "path": [
        "Tricky Invariant"
      ],
      "order": 21,
      "section_order": 5,
      "problem_order": 2,
      "catalog_slug": "in-depth-topics",
      "catalog_name": "In-Depth Topics",
      "premium_only": false,
      "section_premium_only": false,
      "paid_only": false,
      "source_url": "https://leetcode.com/studyplan/binary-search/"
    }
  ],
  "neetcode_subsets": []
}
