{
  "challenge_id": "lc_811",
  "source": "leetcode",
  "frontend_id": "811",
  "slug": "subdomain-visit-count",
  "title": "Subdomain Visit Count",
  "difficulty": "Medium",
  "acceptance_rate": 77.17798186468264,
  "frequency": 38.8,
  "elo_rating": 1377.6120218199,
  "estimated_elo_rating": null,
  "category": "algorithms",
  "category_title": "Algorithms",
  "topics": [
    {
      "name": "Array",
      "slug": "array"
    },
    {
      "name": "Hash Table",
      "slug": "hash-table"
    },
    {
      "name": "String",
      "slug": "string"
    },
    {
      "name": "Counting",
      "slug": "counting"
    }
  ],
  "url": "https://leetcode.com/problems/subdomain-visit-count/",
  "supported_languages": [
    "python",
    "cpp",
    "java",
    "csharp",
    "javascript",
    "go",
    "kotlin"
  ],
  "primary_language": "python",
  "runnable_in_coden": true,
  "subsets": [
    "leetcode_all",
    "leetcode_category:algorithms",
    "leetcode_company:google",
    "leetcode_company:roblox",
    "leetcode_company:wix",
    "leetcode_topic:array",
    "leetcode_topic:counting",
    "leetcode_topic:hash-table",
    "leetcode_topic:string"
  ],
  "tags": [
    "category:algorithms",
    "company:google",
    "company:roblox",
    "company:wix",
    "language:cpp",
    "language:csharp",
    "language:go",
    "language:java",
    "language:javascript",
    "language:kotlin",
    "language:python",
    "leetcode",
    "topic:array",
    "topic:counting",
    "topic:hash-table",
    "topic:string"
  ],
  "company_tags": [
    {
      "name": "Google",
      "slug": "google"
    },
    {
      "name": "Roblox",
      "slug": "roblox"
    },
    {
      "name": "Wix",
      "slug": "wix"
    }
  ],
  "company_tag_stats": {
    "3": [
      {
        "taggedByAdmin": true,
        "name": "Roblox",
        "slug": "roblox",
        "timesEncountered": 0
      },
      {
        "taggedByAdmin": true,
        "name": "Wix",
        "slug": "wix",
        "timesEncountered": 0
      }
    ],
    "1": [
      {
        "taggedByAdmin": false,
        "name": "Google",
        "slug": "google",
        "timesEncountered": 2
      }
    ],
    "2": []
  },
  "neetcode_subsets": []
}
