{
  "challenge_id": "lc_971",
  "source": "leetcode",
  "frontend_id": "971",
  "slug": "flip-binary-tree-to-match-preorder-traversal",
  "title": "Flip Binary Tree To Match Preorder Traversal",
  "difficulty": "Medium",
  "acceptance_rate": 52.006370744218756,
  "frequency": 0.0,
  "elo_rating": 1786.5491561897,
  "estimated_elo_rating": null,
  "category": "algorithms",
  "category_title": "Algorithms",
  "topics": [
    {
      "name": "Tree",
      "slug": "tree"
    },
    {
      "name": "Depth-First Search",
      "slug": "depth-first-search"
    },
    {
      "name": "Binary Tree",
      "slug": "binary-tree"
    }
  ],
  "url": "https://leetcode.com/problems/flip-binary-tree-to-match-preorder-traversal/",
  "supported_languages": [
    "python",
    "cpp",
    "java",
    "csharp",
    "javascript",
    "go",
    "kotlin"
  ],
  "primary_language": "python",
  "runnable_in_coden": true,
  "solution_variants": {
    "manifest": "solution_variants.json",
    "default": "optimal"
  },
  "subsets": [
    "leetcode_all",
    "leetcode_category:algorithms",
    "leetcode_topic:binary-tree",
    "leetcode_topic:depth-first-search",
    "leetcode_topic:tree"
  ],
  "tags": [
    "category:algorithms",
    "language:cpp",
    "language:csharp",
    "language:go",
    "language:java",
    "language:javascript",
    "language:kotlin",
    "language:python",
    "leetcode",
    "topic:binary-tree",
    "topic:depth-first-search",
    "topic:tree"
  ],
  "company_tags": [],
  "company_tag_stats": {
    "1": [],
    "2": [],
    "3": []
  },
  "neetcode_subsets": []
}
