{
  "challenge_id": "lc_2594",
  "source": "leetcode",
  "frontend_id": "2594",
  "slug": "minimum-time-to-repair-cars",
  "title": "Minimum Time to Repair Cars",
  "difficulty": "Medium",
  "acceptance_rate": 59.503317635773826,
  "frequency": 40.3,
  "elo_rating": 1915.2628132733,
  "estimated_elo_rating": null,
  "category": "algorithms",
  "category_title": "Algorithms",
  "topics": [
    {
      "name": "Array",
      "slug": "array"
    },
    {
      "name": "Binary Search",
      "slug": "binary-search"
    }
  ],
  "url": "https://leetcode.com/problems/minimum-time-to-repair-cars/",
  "supported_languages": [
    "python",
    "cpp",
    "java",
    "csharp",
    "javascript",
    "go",
    "kotlin"
  ],
  "primary_language": "python",
  "runnable_in_coden": true,
  "subsets": [
    "leetcode_all",
    "leetcode_category:algorithms",
    "leetcode_company:amazon",
    "leetcode_company:deloitte",
    "leetcode_company:facebook",
    "leetcode_company:google",
    "leetcode_company:hashedin",
    "leetcode_company:microsoft",
    "leetcode_topic:array",
    "leetcode_topic:binary-search",
    "neetcode:allNC"
  ],
  "tags": [
    "category:algorithms",
    "company:amazon",
    "company:deloitte",
    "company:facebook",
    "company:google",
    "company:hashedin",
    "company:microsoft",
    "language:cpp",
    "language:csharp",
    "language:go",
    "language:java",
    "language:javascript",
    "language:kotlin",
    "language:python",
    "leetcode",
    "subset:neetcode:allNC",
    "topic:array",
    "topic:binary-search"
  ],
  "company_tags": [
    {
      "name": "Meta",
      "slug": "facebook"
    },
    {
      "name": "Microsoft",
      "slug": "microsoft"
    },
    {
      "name": "Google",
      "slug": "google"
    },
    {
      "name": "Amazon",
      "slug": "amazon"
    },
    {
      "name": "HashedIn",
      "slug": "hashedin"
    },
    {
      "name": "Deloitte",
      "slug": "deloitte"
    }
  ],
  "company_tag_stats": {
    "3": [
      {
        "taggedByAdmin": false,
        "name": "Google",
        "slug": "google",
        "timesEncountered": 7
      },
      {
        "taggedByAdmin": false,
        "name": "Amazon",
        "slug": "amazon",
        "timesEncountered": 3
      },
      {
        "taggedByAdmin": false,
        "name": "HashedIn",
        "slug": "hashedin",
        "timesEncountered": 2
      },
      {
        "taggedByAdmin": false,
        "name": "Deloitte",
        "slug": "deloitte",
        "timesEncountered": 2
      }
    ],
    "2": [
      {
        "taggedByAdmin": false,
        "name": "Meta",
        "slug": "facebook",
        "timesEncountered": 2
      },
      {
        "taggedByAdmin": false,
        "name": "Microsoft",
        "slug": "microsoft",
        "timesEncountered": 2
      }
    ],
    "1": []
  },
  "neetcode_subsets": [
    {
      "kind": "neetcode",
      "subset_slug": "allNC",
      "subset_name": "NeetCode All",
      "subset_order": 4,
      "path": [
        "Binary Search"
      ],
      "order": 321,
      "section_order": 4,
      "source_url": "https://neetcode.io/practice/practice/allNC",
      "neetcode_slug": "minimum-time-to-repair-cars",
      "leetcode_slug": "minimum-time-to-repair-cars",
      "difficulty": "Medium",
      "problem_order": 23
    }
  ]
}
