{"schema_version":1,"challenge_id":"lc_1024","cases":[
{"id":"sample-1","name":"sample: three overlapping clips","kind":"sample","visible":true,"input":{"clips":[[0,2],[4,6],[8,10],[1,9],[1,5],[5,9]],"time":10},"expected":3,"tags":["sample"]},
{"id":"sample-2","name":"sample: impossible tail gap","kind":"sample","visible":true,"input":{"clips":[[0,1],[1,2]],"time":5},"expected":-1,"tags":["sample"]},
{"id":"sample-3","name":"sample: dense interval collection","kind":"sample","visible":true,"input":{"clips":[[0,1],[6,8],[0,2],[5,6],[0,4],[0,3],[6,7],[1,3],[4,7],[1,4],[2,5],[2,6],[3,4],[4,5],[5,7],[6,9]],"time":9},"expected":3,"tags":["sample"]},
{"id":"trial-1","name":"trial: one clip covers target","kind":"trial","visible":true,"input":{"clips":[[0,5]],"time":5},"expected":1,"tags":["trial","single"]},
{"id":"trial-2","name":"trial: gap at beginning","kind":"trial","visible":true,"input":{"clips":[[1,5],[2,6]],"time":5},"expected":-1,"tags":["trial","initial-gap"]},
{"id":"trial-3","name":"trial: exact unit chain","kind":"trial","visible":true,"input":{"clips":[[0,1],[1,2],[2,3]],"time":3},"expected":3,"tags":["trial","chain"]},
{"id":"hidden-1","name":"hidden: farthest overlap wins","kind":"real","visible":false,"input":{"clips":[[0,4],[2,8],[5,10],[8,12]],"time":10},"expected":3,"tags":["hidden","greedy"]},
{"id":"hidden-2","name":"hidden: redundant same-start clips","kind":"real","visible":false,"input":{"clips":[[0,1],[0,3],[0,2],[3,6],[2,5]],"time":6},"expected":2,"tags":["hidden","redundant"]},
{"id":"hidden-3","name":"hidden: zero-length clips do not extend","kind":"real","visible":false,"input":{"clips":[[0,0],[0,2],[2,2],[2,4]],"time":4},"expected":2,"tags":["hidden","zero-length"]}
]}
