{
  "challenge_id": "lc_3459",
  "source": "leetcode",
  "frontend_id": "3459",
  "slug": "length-of-longest-v-shaped-diagonal-segment",
  "title": "Length of Longest V-Shaped Diagonal Segment",
  "difficulty": "Hard",
  "acceptance_rate": 56.172531214528945,
  "frequency": 44.7,
  "elo_rating": 2530.6462600383,
  "estimated_elo_rating": null,
  "category": "algorithms",
  "category_title": "Algorithms",
  "topics": [
    {
      "name": "Array",
      "slug": "array"
    },
    {
      "name": "Dynamic Programming",
      "slug": "dynamic-programming"
    },
    {
      "name": "Memoization",
      "slug": "memoization"
    },
    {
      "name": "Matrix",
      "slug": "matrix"
    }
  ],
  "url": "https://leetcode.com/problems/length-of-longest-v-shaped-diagonal-segment/",
  "supported_languages": [
    "python",
    "cpp",
    "java",
    "csharp",
    "javascript",
    "go",
    "kotlin"
  ],
  "primary_language": "python",
  "runnable_in_coden": true,
  "solution_variants": {
    "manifest": "solution_variants.json",
    "default": "optimal"
  },
  "subsets": [
    "leetcode_all",
    "leetcode_category:algorithms",
    "leetcode_company:amazon",
    "leetcode_company:roblox",
    "leetcode_company:visa",
    "leetcode_topic:array",
    "leetcode_topic:dynamic-programming",
    "leetcode_topic:matrix",
    "leetcode_topic:memoization"
  ],
  "tags": [
    "category:algorithms",
    "company:amazon",
    "company:roblox",
    "company:visa",
    "language:cpp",
    "language:csharp",
    "language:go",
    "language:java",
    "language:javascript",
    "language:kotlin",
    "language:python",
    "leetcode",
    "topic:array",
    "topic:dynamic-programming",
    "topic:matrix",
    "topic:memoization"
  ],
  "company_tags": [
    {
      "name": "Amazon",
      "slug": "amazon"
    },
    {
      "name": "Roblox",
      "slug": "roblox"
    },
    {
      "name": "Visa",
      "slug": "visa"
    }
  ],
  "company_tag_stats": {
    "3": [
      {
        "taggedByAdmin": false,
        "name": "Visa",
        "slug": "visa",
        "timesEncountered": 7
      }
    ],
    "2": [
      {
        "taggedByAdmin": false,
        "name": "Amazon",
        "slug": "amazon",
        "timesEncountered": 3
      },
      {
        "taggedByAdmin": false,
        "name": "Roblox",
        "slug": "roblox",
        "timesEncountered": 2
      }
    ],
    "1": []
  },
  "neetcode_subsets": []
}
