{
  "challenge_id": "lc_1566",
  "source": "leetcode",
  "frontend_id": "1566",
  "slug": "detect-pattern-of-length-m-repeated-k-or-more-times",
  "title": "Detect Pattern of Length M Repeated K or More Times",
  "difficulty": "Easy",
  "acceptance_rate": 44.07909374072975,
  "category": "algorithms",
  "category_title": "Algorithms",
  "topics": [
    {
      "name": "Array",
      "slug": "array"
    },
    {
      "name": "Enumeration",
      "slug": "enumeration"
    }
  ],
  "url": "https://leetcode.com/problems/detect-pattern-of-length-m-repeated-k-or-more-times/",
  "supported_languages": [
    "python",
    "cpp",
    "java",
    "csharp",
    "javascript",
    "go",
    "kotlin"
  ],
  "primary_language": "python",
  "runnable_in_coden": true,
  "subsets": [
    "leetcode_all",
    "leetcode_category:algorithms",
    "leetcode_company:hrt",
    "leetcode_topic:array",
    "leetcode_topic:enumeration"
  ],
  "tags": [
    "category:algorithms",
    "company:hrt",
    "language:cpp",
    "language:csharp",
    "language:go",
    "language:java",
    "language:javascript",
    "language:kotlin",
    "language:python",
    "leetcode",
    "topic:array",
    "topic:enumeration"
  ],
  "company_tags": [
    {
      "name": "Hudson River Trading",
      "slug": "hrt"
    }
  ],
  "company_tag_stats": {
    "3": [
      {
        "taggedByAdmin": true,
        "name": "Hudson River Trading",
        "slug": "hrt",
        "timesEncountered": 0
      }
    ],
    "1": [],
    "2": []
  },
  "neetcode_subsets": []
}
