{
  "challenge_id": "lc_2157",
  "source": "leetcode",
  "frontend_id": "2157",
  "slug": "groups-of-strings",
  "title": "Groups of Strings",
  "difficulty": "Hard",
  "acceptance_rate": 28.00378429517502,
  "frequency": 0.0,
  "elo_rating": 2499.3282271507,
  "estimated_elo_rating": null,
  "category": "algorithms",
  "category_title": "Algorithms",
  "topics": [
    {
      "name": "Array",
      "slug": "array"
    },
    {
      "name": "Hash Table",
      "slug": "hash-table"
    },
    {
      "name": "String",
      "slug": "string"
    },
    {
      "name": "Bit Manipulation",
      "slug": "bit-manipulation"
    },
    {
      "name": "Union-Find",
      "slug": "union-find"
    }
  ],
  "url": "https://leetcode.com/problems/groups-of-strings/",
  "supported_languages": [
    "python",
    "cpp",
    "java",
    "csharp",
    "javascript",
    "go",
    "kotlin"
  ],
  "primary_language": "python",
  "runnable_in_coden": true,
  "subsets": [
    "leetcode_all",
    "leetcode_category:algorithms",
    "leetcode_company:lowe",
    "leetcode_topic:array",
    "leetcode_topic:bit-manipulation",
    "leetcode_topic:hash-table",
    "leetcode_topic:string",
    "leetcode_topic:union-find"
  ],
  "tags": [
    "category:algorithms",
    "company:lowe",
    "language:cpp",
    "language:csharp",
    "language:go",
    "language:java",
    "language:javascript",
    "language:kotlin",
    "language:python",
    "leetcode",
    "topic:array",
    "topic:bit-manipulation",
    "topic:hash-table",
    "topic:string",
    "topic:union-find"
  ],
  "company_tags": [
    {
      "name": "Lowe's",
      "slug": "lowe"
    }
  ],
  "company_tag_stats": {
    "3": [
      {
        "taggedByAdmin": true,
        "name": "Lowe's",
        "slug": "lowe",
        "timesEncountered": 0
      }
    ],
    "1": [],
    "2": []
  },
  "neetcode_subsets": []
}
